{
    "area": [
        "north",
        "centre",
        "east",
        "west",
        "south"
    ],
    "bookday": [
        "monday",
        "friday",
        "thursday",
        "sunday",
        "tuesday",
        "saturday",
        "wednesday"
    ],
    "bookpeople": [
        "5",
        "3",
        "6",
        "2",
        "1",
        "4",
        "8",
        "7"
    ],
    "bookstay": [
        "4",
        "5",
        "2",
        "1",
        "3",
        "6",
        "7",
        "8"
    ],
    "internet": [
        "yes",
        "no",
        "free"
    ],
    "name": [
        "Huntingdon Marriott",
        "huntingdon marriott",
        "huntingdon marriott hotel",
        "university arms hotel",
        "Home from Home",
        "home from home",
        "Rosa's",
        "rosas bed and breakfast",
        "rosa's",
        "Acorn guest house",
        "acorn guest house",
        "gonville hotel",
        "bridge guest house",
        "University Arms Hotel",
        "Finches Bed and Breakfast",
        "finches bed and breakfast",
        "cambridge belfry",
        "allenbell",
        "Cambridge Belfry",
        "Huntingdon Marriott Hotel",
        "Ashley Hotel",
        "ashley hotel",
        "acorn guest House",
        "Allenbell",
        "B Guesthouse",
        "a and b guest house",
        "b guesthouse",
        "alpha-milton guest house",
        "Acorn",
        "acorn",
        "Worth House",
        "worth house",
        "express by holiday inn cambridge",
        "Lovell Lodge",
        "lovell lodge",
        "alexander bed and breakfast",
        "Cityroomz",
        "cityroomz",
        "Acorn Guest House",
        "city centre north b and b",
        "A and B Guest House",
        "avalon",
        "Warkworth House",
        "warkworth house",
        "Arbury Lodge Guesthouse",
        "arbury lodge guesthouse",
        "Autumn House",
        "autumn house",
        "Gonville",
        "gonville",
        "Huntington Marriott Hotel",
        "huntington marriott hotel",
        "Carolina bed and breakfast",
        "carolina bed and breakfast",
        "Hamilton Lodge",
        "hamilton lodge",
        "Hobsons house",
        "hobsons house",
        "Gonville Hotel",
        "Carolina Bed and Breakfast",
        "Arbury Lodge",
        "arbury lodge",
        "Lensfield Hotel",
        "lensfield hotel",
        "Cambridge belfry",
        "Finches bed and breakfast",
        "Huntington Marriott",
        "huntington marriott",
        "City Centre North B And B",
        "Alexander Bed and Breakfast",
        "Alpha Milton guesthouse",
        "alpha milton guesthouse",
        "A and B guest house",
        "City Centre North B & B",
        "city centre north b & b",
        "Lensfield hotel",
        "aylesbray lodge guest house",
        "kirkwood house",
        "Ashley hotel",
        "Huntingdon Marriot",
        "huntingdon marriot",
        "el shaddai",
        "el shaddia guesthouse",
        "Aylesbray Lodge Guest House",
        "Alexander bed and breakfast",
        "Avalon",
        "El Shaddai",
        "Alpha-Milton Guest House",
        "University Arms",
        "university arms",
        "Gonville hotel",
        "Bridge Guest House",
        "Limehouse",
        "limehouse",
        "Alexander B&B",
        "alexander b&b",
        "City Centre North B and B",
        "Archway House",
        "archway house",
        "Acorn Guesthouse",
        "acorn guesthouse",
        "alpha-milton guest",
        "Aylesbray Lodge guest house",
        "Aylesbray Lodge",
        "aylesbray lodge",
        "bridge house",
        "Leverton House",
        "leverton house",
        "alexander",
        "Express by Holiday Inn Cambridge",
        "citiroomz",
        "Autumn house",
        "belfry",
        "Hobsons House",
        "rosas's bed and breakfast",
        "express by holiday Inn in cambridge",
        "express by holiday inn in cambridge",
        "Alpha-milton guest house",
        "Holiday Inn Cambridge",
        "holiday inn cambridge",
        "Ashely Hotel",
        "ashely hotel",
        "Lovell lodge",
        "Alpha-Milton guest house",
        "Finches",
        "finches",
        "Lodge Guesthouse",
        "lodge guesthouse",
        "City centre north b and b",
        "Kirkwood House",
        "Alpha Milton guest house",
        "alpha milton guest house",
        "acorn house",
        "Marriott Hotel",
        "marriott hotel",
        "marriot hotel",
        "University Arms hotel",
        "Hobson's House",
        "hobson's house",
        "Alpha-Milton Guest house",
        "express by Holiday Inn Cambridge",
        "Rosa's b&b",
        "rosa's b&b",
        "Belfry",
        "Bridge Guesthouse",
        "bridge guesthouse",
        "rose's bed and breakfast",
        "Alexander",
        "university Arms Hotel",
        "El shaddai",
        "alexander bed and breakfastin",
        "University arms hotel",
        "kirkwood",
        "City Centre North B&B",
        "city centre north b&b",
        "Lensfield",
        "lensfield",
        "Huntingdon Marriott hotel",
        "City Centre B and B",
        "city centre b and b",
        "Alpha Milton Guest House",
        "Lensdield Hotel",
        "lensdield hotel",
        "Huntingdon marriott hotel",
        "Acorn guesthouse",
        "ALexeander b&b",
        "alexeander b&b",
        "the Alexander Bed and Breakfast",
        "the alexander bed and breakfast",
        "Acorn House"
    ],
    "parking": [
        "yes",
        "no",
        "free"
    ],
    "price_range": [
        "expensive",
        "cheap",
        "moderate"
    ],
    "stars": [
        "4",
        "3",
        "5",
        "1",
        "0",
        "2"
    ],
    "type": [
        "hotel",
        "guesthouse"
    ]
}